Workbook

Sheet Employee Master
A1: Employee Master Data
A2: Practice file — HR Analytics Workbook
A4: Emp ID | B4: First Name | C4: Last Name | D4: Department | E4: Designation | F4: Gender | G4: City | H4: Date of Joining | I4: Date of Birth | J4: Employment Status | K4: Annual CTC (INR) | L4: Basic Salary (Monthly) | M4: HRA (Monthly)
A5: EMP1000 | B5: Wei | C5: Reddy | D5: Engineering | E5: Engineering Manager | F5: Male | G5: Pune | H5: 42941 | I5: 29074 | J5: Active | K5: 670000 | L5: 22330 | M5: 8930
A6: EMP1001 | B6: Harper | C6: Brown | D6: Engineering | E6: Software Engineer | F6: Male | G6: Pune | H6: 43322 | I6: 35674 | J6: On Leave | K6: 510000 | L6: 17000 | M6: 6800
A7: EMP1002 | B7: Charlotte | C7: Rao | D7: Operations | E7: Logistics Coordinator | F7: Female | G7: Pune | H7: 44209 | I7: 37049 | J7: Active | K7: 460000 | L7: 15330 | M7: 6130
A8: EMP1003 | B8: Sofia | C8: Chatterjee | D8: Sales | E8: Business Development Rep | F8: Female | G8: Chennai | H8: 43006 | I8: 30922 | J8: Terminated | K8: 1310000 | L8: 43670 | M8: 17470
A9: EMP1004 | B9: Reyansh | C9: Gupta | D9: HR | E9: HR Executive | F9: Female | G9: Delhi | H9: 44842 | I9: 31728 | J9: Terminated | K9: 560000 | L9: 18670 | M9: 7470
A10: EMP1005 | B10: Min | C10: Jones | D10: Finance | E10: Accountant | F10: Female | G10: Bengaluru | H10: 44631 | I10: 32198 | J10: Terminated | K10: 1370000 | L10: 45670 | M10: 18270
A11: EMP1006 | B11: Amelia | C11: Rao | D11: Operations | E11: Operations Executive | F11: Male | G11: Pune | H11: 45536 | I11: 32136 | J11: Active | K11: 1040000 | L11: 34670 | M11: 13870
A12: EMP1007 | B12: Reyansh | C12: Williams | D12: Marketing | E12: SEO Specialist | F12: Female | G12: Mumbai | H12: 43886 | I12: 33215 | J12: Active | K12: 1130000 | L12: 37670 | M12: 15070
A13: EMP1008 | B13: Chen | C13: Mukherjee | D13: Operations | E13: Logistics Coordinator | F13: Male | G13: Mumbai | H13: 44557 | I13: 31405 | J13: Active | K13: 1630000 | L13: 54330 | M13: 21730
A14: EMP1009 | B14: David | C14: Kapoor | D14: Operations | E14: Logistics Coordinator | F14: Male | G14: Delhi | H14: 45822 | I14: 28311 | J14: Active | K14: 530000 | L14: 17670 | M14: 7070
A15: EMP1010 | B15: James | C15: Williams | D15: Marketing | E15: Marketing Executive | F15: Male | G15: Delhi | H15: 43240 | I15: 35574 | J15: Active | K15: 1620000 | L15: 54000 | M15: 21600
A16: EMP1011 | B16: Rohan | C16: Kapoor | D16: Sales | E16: Account Manager | F16: Female | G16: Gurugram | H16: 44760 | I16: 33938 | J16: Active | K16: 1010000 | L16: 33670 | M16: 13470
... A124: EMP1119 | B124: Reyansh | C124: Mehta | D124: HR | E124: Talent Acquisition Specialist | F124: Female | G124: Chennai | H124: 42459 | I124: 33879 | J124: Active | K124: 470000 | L124: 15670 | M124: 6270

Sheet Attendance - June 2026
A1: Monthly Attendance Tracker — June 2026
A2: P = Present, A = Absent, L = Leave, WO = Week Off
A4: Emp ID | B4: Name | C4: Department | D4: Days Present | E4: Days Absent | F4: Days on Leave | G4: Working Days | H4: Attendance %
A5: ='Employee Master'!A5 -> EMP1000 | B5: =CONCATENATE('Employee Master'!B5," ",'Employee Master'!C5) -> Wei Reddy | C5: ='Employee Master'!D5 -> Engineering | D5: 14 | E5: 3 | F5: 5 | G5: 22 | H5: =D5/G5 -> 0.63636364
A6: ='Employee Master'!A6 -> EMP1001 | B6: =CONCATENATE('Employee Master'!B6," ",'Employee Master'!C6) -> Harper Brown | C6: ='Employee Master'!D6 -> Engineering | D6: 18 | E6: 1 | F6: 3 | G6: 22 | H6: =D6/G6 -> 0.81818182
A7: ='Employee Master'!A7 -> EMP1002 | B7: =CONCATENATE('Employee Master'!B7," ",'Employee Master'!C7) -> Charlotte Rao | C7: ='Employee Master'!D7 -> Operations | D7: 19 | E7: 1 | F7: 2 | G7: 22 | H7: =D7/G7 -> 0.86363636
A8: ='Employee Master'!A8 -> EMP1003 | B8: =CONCATENATE('Employee Master'!B8," ",'Employee Master'!C8) -> Sofia Chatterjee | C8: ='Employee Master'!D8 -> Sales | D8: 17 | E8: 2 | F8: 3 | G8: 22 | H8: =D8/G8 -> 0.77272727
A9: ='Employee Master'!A9 -> EMP1004 | B9: =CONCATENATE('Employee Master'!B9," ",'Employee Master'!C9) -> Reyansh Gupta | C9: ='Employee Master'!D9 -> HR | D9: 16 | E9: 0 | F9: 6 | G9: 22 | H9: =D9/G9 -> 0.72727273
A10: ='Employee Master'!A10 -> EMP1005 | B10: =CONCATENATE('Employee Master'!B10," ",'Employee Master'!C10) -> Min Jones | C10: ='Employee Master'!D10 -> Finance | D10: 14 | E10: 2 | F10: 6 | G10: 22 | H10: =D10/G10 -> 0.63636364
A11: ='Employee Master'!A11 -> EMP1006 | B11: =CONCATENATE('Employee Master'!B11," ",'Employee Master'!C11) -> Amelia Rao | C11: ='Employee Master'!D11 -> Operations | D11: 21 | E11: 0 | F11: 1 | G11: 22 | H11: =D11/G11 -> 0.95454545
A12: ='Employee Master'!A12 -> EMP1007 | B12: =CONCATENATE('Employee Master'!B12," ",'Employee Master'!C12) -> Reyansh Williams | C12: ='Employee Master'!D12 -> Marketing | D12: 19 | E12: 1 | F12: 2 | G12: 22 | H12: =D12/G12 -> 0.86363636
A13: ='Employee Master'!A13 -> EMP1008 | B13: =CONCATENATE('Employee Master'!B13," ",'Employee Master'!C13) -> Chen Mukherjee | C13: ='Employee Master'!D13 -> Operations | D13: 15 | E13: 2 | F13: 5 | G13: 22 | H13: =D13/G13 -> 0.68181818
A14: ='Employee Master'!A14 -> EMP1009 | B14: =CONCATENATE('Employee Master'!B14," ",'Employee Master'!C14) -> David Kapoor | C14: ='Employee Master'!D14 -> Operations | D14: 19 | E14: 3 | F14: 0 | G14: 22 | H14: =D14/G14 -> 0.86363636
A15: ='Employee Master'!A15 -> EMP1010 | B15: =CONCATENATE('Employee Master'!B15," ",'Employee Master'!C15) -> James Williams | C15: ='Employee Master'!D15 -> Marketing | D15: 16 | E15: 1 | F15: 5 | G15: 22 | H15: =D15/G15 -> 0.72727273
A16: ='Employee Master'!A16 -> EMP1011 | B16: =CONCATENATE('Employee Master'!B16," ",'Employee Master'!C16) -> Rohan Kapoor | C16: ='Employee Master'!D16 -> Sales | D16: 16 | E16: 2 | F16: 4 | G16: 22 | H16: =D16/G16 -> 0.72727273
... A124: ='Employee Master'!A124 -> EMP1119 | B124: =CONCATENATE('Employee Master'!B124," ",'Employee Master'!C124) -> Reyansh Mehta | C124: ='Employee Master'!D124 -> HR | D124: 21 | E124: 1 | F124: 0 | G124: 22 | H124: =D124/G124 -> 0.95454545

Sheet Payroll Calculation
A1: Payroll Calculation — June 2026
A2: PF = 12% of Basic (capped 1,800/mo) | Prof. Tax = 200 flat | Net Pay = Gross - Deductions
A4: Emp ID | B4: Name | C4: Department | D4: Basic Salary | E4: HRA | F4: Conveyance Allowance | G4: Gross Salary | H4: PF Deduction (12%) | I4: Professional Tax | J4: Total Deductions | K4: Net Pay | M4: Assumptions
A5: ='Employee Master'!A5 -> EMP1000 | B5: =CONCATENATE('Employee Master'!B5," ",'Employee Master'!C5) -> Wei Reddy | C5: ='Employee Master'!D5 -> Engineering | D5: ='Employee Master'!L5 -> 22330 | E5: ='Employee Master'!M5 -> 8930 | F5: =$N$5 -> 1600 | G5: =D5+E5+F5 -> 32860 | H5: =MIN(D5*$N$6,$N$7) -> 1800 | I5: =$N$8 -> 200 | J5: =H5+I5 -> 2000 | K5: =G5-J5 -> 30860 | M5: Conveyance Allowance (flat) | N5: 1600
A6: ='Employee Master'!A6 -> EMP1001 | B6: =CONCATENATE('Employee Master'!B6," ",'Employee Master'!C6) -> Harper Brown | C6: ='Employee Master'!D6 -> Engineering | D6: ='Employee Master'!L6 -> 17000 | E6: ='Employee Master'!M6 -> 6800 | F6: =$N$5 -> 1600 | G6: =D6+E6+F6 -> 25400 | H6: =MIN(D6*$N$6,$N$7) -> 1800 | I6: =$N$8 -> 200 | J6: =H6+I6 -> 2000 | K6: =G6-J6 -> 23400 | M6: PF Rate | N6: 0.12
A7: ='Employee Master'!A7 -> EMP1002 | B7: =CONCATENATE('Employee Master'!B7," ",'Employee Master'!C7) -> Charlotte Rao | C7: ='Employee Master'!D7 -> Operations | D7: ='Employee Master'!L7 -> 15330 | E7: ='Employee Master'!M7 -> 6130 | F7: =$N$5 -> 1600 | G7: =D7+E7+F7 -> 23060 | H7: =MIN(D7*$N$6,$N$7) -> 1800 | I7: =$N$8 -> 200 | J7: =H7+I7 -> 2000 | K7: =G7-J7 -> 21060 | M7: PF Monthly Cap | N7: 1800
A8: ='Employee Master'!A8 -> EMP1003 | B8: =CONCATENATE('Employee Master'!B8," ",'Employee Master'!C8) -> Sofia Chatterjee | C8: ='Employee Master'!D8 -> Sales | D8: ='Employee Master'!L8 -> 43670 | E8: ='Employee Master'!M8 -> 17470 | F8: =$N$5 -> 1600 | G8: =D8+E8+F8 -> 62740 | H8: =MIN(D8*$N$6,$N$7) -> 1800 | I8: =$N$8 -> 200 | J8: =H8+I8 -> 2000 | K8: =G8-J8 -> 60740 | M8: Professional Tax (flat) | N8: 200
A9: ='Employee Master'!A9 -> EMP1004 | B9: =CONCATENATE('Employee Master'!B9," ",'Employee Master'!C9) -> Reyansh Gupta | C9: ='Employee Master'!D9 -> HR | D9: ='Employee Master'!L9 -> 18670 | E9: ='Employee Master'!M9 -> 7470 | F9: =$N$5 -> 1600 | G9: =D9+E9+F9 -> 27740 | H9: =MIN(D9*$N$6,$N$7) -> 1800 | I9: =$N$8 -> 200 | J9: =H9+I9 -> 2000 | K9: =G9-J9 -> 25740
A10: ='Employee Master'!A10 -> EMP1005 | B10: =CONCATENATE('Employee Master'!B10," ",'Employee Master'!C10) -> Min Jones | C10: ='Employee Master'!D10 -> Finance | D10: ='Employee Master'!L10 -> 45670 | E10: ='Employee Master'!M10 -> 18270 | F10: =$N$5 -> 1600 | G10: =D10+E10+F10 -> 65540 | H10: =MIN(D10*$N$6,$N$7) -> 1800 | I10: =$N$8 -> 200 | J10: =H10+I10 -> 2000 | K10: =G10-J10 -> 63540
A11: ='Employee Master'!A11 -> EMP1006 | B11: =CONCATENATE('Employee Master'!B11," ",'Employee Master'!C11) -> Amelia Rao | C11: ='Employee Master'!D11 -> Operations | D11: ='Employee Master'!L11 -> 34670 | E11: ='Employee Master'!M11 -> 13870 | F11: =$N$5 -> 1600 | G11: =D11+E11+F11 -> 50140 | H11: =MIN(D11*$N$6,$N$7) -> 1800 | I11: =$N$8 -> 200 | J11: =H11+I11 -> 2000 | K11: =G11-J11 -> 48140
A12: ='Employee Master'!A12 -> EMP1007 | B12: =CONCATENATE('Employee Master'!B12," ",'Employee Master'!C12) -> Reyansh Williams | C12: ='Employee Master'!D12 -> Marketing | D12: ='Employee Master'!L12 -> 37670 | E12: ='Employee Master'!M12 -> 15070 | F12: =$N$5 -> 1600 | G12: =D12+E12+F12 -> 54340 | H12: =MIN(D12*$N$6,$N$7) -> 1800 | I12: =$N$8 -> 200 | J12: =H12+I12 -> 2000 | K12: =G12-J12 -> 52340
A13: ='Employee Master'!A13 -> EMP1008 | B13: =CONCATENATE('Employee Master'!B13," ",'Employee Master'!C13) -> Chen Mukherjee | C13: ='Employee Master'!D13 -> Operations | D13: ='Employee Master'!L13 -> 54330 | E13: ='Employee Master'!M13 -> 21730 | F13: =$N$5 -> 1600 | G13: =D13+E13+F13 -> 77660 | H13: =MIN(D13*$N$6,$N$7) -> 1800 | I13: =$N$8 -> 200 | J13: =H13+I13 -> 2000 | K13: =G13-J13 -> 75660
A14: ='Employee Master'!A14 -> EMP1009 | B14: =CONCATENATE('Employee Master'!B14," ",'Employee Master'!C14) -> David Kapoor | C14: ='Employee Master'!D14 -> Operations | D14: ='Employee Master'!L14 -> 17670 | E14: ='Employee Master'!M14 -> 7070 | F14: =$N$5 -> 1600 | G14: =D14+E14+F14 -> 26340 | H14: =MIN(D14*$N$6,$N$7) -> 1800 | I14: =$N$8 -> 200 | J14: =H14+I14 -> 2000 | K14: =G14-J14 -> 24340
A15: ='Employee Master'!A15 -> EMP1010 | B15: =CONCATENATE('Employee Master'!B15," ",'Employee Master'!C15) -> James Williams | C15: ='Employee Master'!D15 -> Marketing | D15: ='Employee Master'!L15 -> 54000 | E15: ='Employee Master'!M15 -> 21600 | F15: =$N$5 -> 1600 | G15: =D15+E15+F15 -> 77200 | H15: =MIN(D15*$N$6,$N$7) -> 1800 | I15: =$N$8 -> 200 | J15: =H15+I15 -> 2000 | K15: =G15-J15 -> 75200
A16: ='Employee Master'!A16 -> EMP1011 | B16: =CONCATENATE('Employee Master'!B16," ",'Employee Master'!C16) -> Rohan Kapoor | C16: ='Employee Master'!D16 -> Sales | D16: ='Employee Master'!L16 -> 33670 | E16: ='Employee Master'!M16 -> 13470 | F16: =$N$5 -> 1600 | G16: =D16+E16+F16 -> 48740 | H16: =MIN(D16*$N$6,$N$7) -> 1800 | I16: =$N$8 -> 200 | J16: =H16+I16 -> 2000 | K16: =G16-J16 -> 46740
A17: ='Employee Master'!A17 -> EMP1012 | B17: =CONCATENATE('Employee Master'!B17," ",'Employee Master'!C17) -> Ishaan Davis | C17: ='Employee Master'!D17 -> HR | D17: ='Employee Master'!L17 -> 51000 | E17: ='Employee Master'!M17 -> 20400 | F17: =$N$5 -> 1600 | G17: =D17+E17+F17 -> 73000 | H17: =MIN(D17*$N$6,$N$7) -> 1800 | I17: =$N$8 -> 200 | J17: =H17+I17 -> 2000 | K17: =G17-J17 -> 71000
A18: ='Employee Master'!A18 -> EMP1013 | B18: =CONCATENATE('Employee Master'!B18," ",'Employee Master'!C18) -> Evelyn Gupta | C18: ='Employee Master'!D18 -> HR | D18: ='Employee Master'!L18 -> 24670 | E18: ='Employee Master'!M18 -> 9870 | F18: =$N$5 -> 1600 | G18: =D18+E18+F18 -> 36140 | H18: =MIN(D18*$N$6,$N$7) -> 1800 | I18: =$N$8 -> 200 | J18: =H18+I18 -> 2000 | K18: =G18-J18 -> 34140
A19: ='Employee Master'!A19 -> EMP1014 | B19: =CONCATENATE('Employee Master'!B19," ",'Employee Master'!C19) -> Yuki Sen | C19: ='Employee Master'!D19 -> Finance | D19: ='Employee Master'!L19 -> 53670 | E19: ='Employee Master'!M19 -> 21470 | F19: =$N$5 -> 1600 | G19: =D19+E19+F19 -> 76740 | H19: =MIN(D19*$N$6,$N$7) -> 1800 | I19: =$N$8 -> 200 | J19: =H19+I19 -> 2000 | K19: =G19-J19 -> 74740
A20: ='Employee Master'!A20 -> EMP1015 | B20: =CONCATENATE('Employee Master'!B20," ",'Employee Master'!C20) -> Aarav Malhotra | C20: ='Employee Master'!D20 -> Operations | D20: ='Employee Master'!L20 -> 58000 | E20: ='Employee Master'!M20 -> 23200 | F20: =$N$5 -> 1600 | G20: =D20+E20+F20 -> 82800 | H20: =MIN(D20*$N$6,$N$7) -> 1800 | I20: =$N$8 -> 200 | J20: =H20+I20 -> 2000 | K20: =G20-J20 -> 80800
... A124: ='Employee Master'!A124 -> EMP1119 | B124: =CONCATENATE('Employee Master'!B124," ",'Employee Master'!C124) -> Reyansh Mehta | C124: ='Employee Master'!D124 -> HR | D124: ='Employee Master'!L124 -> 15670 | E124: ='Employee Master'!M124 -> 6270 | F124: =$N$5 -> 1600 | G124: =D124+E124+F124 -> 23540 | H124: =MIN(D124*$N$6,$N$7) -> 1800 | I124: =$N$8 -> 200 | J124: =H124+I124 -> 2000 | K124: =G124-J124 -> 21540
C126: TOTAL | D126: =SUM(D5:D124) -> 4559340 | E126: =SUM(E5:E124) -> 1823740 | F126: =SUM(F5:F124) -> 192000 | G126: =SUM(G5:G124) -> 6575080 | H126: =SUM(H5:H124) -> 216000 | I126: =SUM(I5:I124) -> 24000 | J126: =SUM(J5:J124) -> 240000 | K126: =SUM(K5:K124) -> 6335080

Sheet HR Dashboard
A1: HR Analytics Dashboard
A2: Summary metrics built with COUNTIF / SUMIF / AVERAGEIF / COUNTIFS
A4: Headcount by Department
A5: Department | B5: Headcount | C5: Avg CTC (INR) | D5: Avg Attendance %
A6: Engineering | B6: =COUNTIF('Employee Master'!$D$5:$D$124,A6) -> 24 | C6: =AVERAGEIF('Employee Master'!$D$5:$D$124,A6,'Employee Master'!$K$5:$K$124) -> 1116250 | D6: =AVERAGEIF('Attendance - June 2026'!$C$5:$C$124,A6,'Attendance - June 2026'!$H$5:$H$124) -> 0.78219697
A7: Sales | B7: =COUNTIF('Employee Master'!$D$5:$D$124,A7) -> 15 | C7: =AVERAGEIF('Employee Master'!$D$5:$D$124,A7,'Employee Master'!$K$5:$K$124) -> 1155333.3 | D7: =AVERAGEIF('Attendance - June 2026'!$C$5:$C$124,A7,'Attendance - June 2026'!$H$5:$H$124) -> 0.83030303
A8: Marketing | B8: =COUNTIF('Employee Master'!$D$5:$D$124,A8) -> 15 | C8: =AVERAGEIF('Employee Master'!$D$5:$D$124,A8,'Employee Master'!$K$5:$K$124) -> 1097333.3 | D8: =AVERAGEIF('Attendance - June 2026'!$C$5:$C$124,A8,'Attendance - June 2026'!$H$5:$H$124) -> 0.78484848
A9: HR | B9: =COUNTIF('Employee Master'!$D$5:$D$124,A9) -> 16 | C9: =AVERAGEIF('Employee Master'!$D$5:$D$124,A9,'Employee Master'!$K$5:$K$124) -> 1018125 | D9: =AVERAGEIF('Attendance - June 2026'!$C$5:$C$124,A9,'Attendance - June 2026'!$H$5:$H$124) -> 0.80965909
A10: Finance | B10: =COUNTIF('Employee Master'!$D$5:$D$124,A10) -> 23 | C10: =AVERAGEIF('Employee Master'!$D$5:$D$124,A10,'Employee Master'!$K$5:$K$124) -> 1206956.5 | D10: =AVERAGEIF('Attendance - June 2026'!$C$5:$C$124,A10,'Attendance - June 2026'!$H$5:$H$124) -> 0.80039526
A11: Operations | B11: =COUNTIF('Employee Master'!$D$5:$D$124,A11) -> 27 | C11: =AVERAGEIF('Employee Master'!$D$5:$D$124,A11,'Employee Master'!$K$5:$K$124) -> 1190740.7 | D11: =AVERAGEIF('Attendance - June 2026'!$C$5:$C$124,A11,'Attendance - June 2026'!$H$5:$H$124) -> 0.83670034
A14: Key Company Metrics
A15: Total Headcount | B15: =COUNTA('Employee Master'!$A$5:$A$124) -> 120
A16: Active Employees | B16: =COUNTIF('Employee Master'!$J$5:$J$124,"Active") -> 87
A17: Employees on Leave | B17: =COUNTIF('Employee Master'!$J$5:$J$124,"On Leave") -> 19
A18: Terminated Employees | B18: =COUNTIF('Employee Master'!$J$5:$J$124,"Terminated") -> 14
A19: Gender Split - Female | B19: =COUNTIF('Employee Master'!$F$5:$F$124,"Female") -> 56
A20: Gender Split - Male | B20: =COUNTIF('Employee Master'!$F$5:$F$124,"Male") -> 64
A21: Average CTC (INR) | B21: =AVERAGE('Employee Master'!$K$5:$K$124) -> 1139833.3
A22: Highest CTC (INR) | B22: =MAX('Employee Master'!$K$5:$K$124) -> 1800000
A23: Total Monthly Payroll (Net) | B23: =SUM('Payroll Calculation'!$K$5:$K$124) -> 6335080
A24: Employees with Attendance < 80% | B24: =COUNTIF('Attendance - June 2026'!$H$5:$H$124,"<0.8") -> 58

Sheet Practice Exercises
A1: Practice Exercises
A2: Try these using the data in 'Employee Master', 'Attendance', and 'Payroll Calculation' tabs. Write your formulas in column C.
A4: # | B4: Task | C4: Your Formula / Answer
A5: 1 | B5: Use VLOOKUP to find the Department of employee 'EMP1010' on this sheet.
A6: 2 | B6: Count how many employees joined after 1-Jan-2022 (use COUNTIF or COUNTIFS with dates).
A7: 3 | B7: Calculate each employee's tenure in years as of today using DATEDIF (Employee Master sheet).
A8: 4 | B8: Calculate each employee's current age using DATEDIF on Date of Birth.
A9: 5 | B9: Find the employee with the highest Annual CTC using INDEX/MATCH.
A10: 6 | B10: Count the number of employees in the 'Engineering' department using COUNTIF.
A11: 7 | B11: Calculate the average Attendance % for employees in the 'Sales' department using AVERAGEIF.
A12: 8 | B12: Use IF to flag employees with Attendance % below 85% as 'At Risk', else 'OK'.
A13: 9 | B13: Use SUMIFS to total Net Pay for employees in the 'Finance' department only.
A14: 10 | B14: Create a formula to concatenate First Name + Last Name + Department into one string.
A15: 11 | B15: Use COUNTIFS to count Active female employees in Bengaluru.
A16: 12 | B16: Rank employees by Annual CTC within their department using RANK or RANK.EQ + array logic.
... A19: 15 | B19: Use TEXT() to format each employee's Date of Joining as 'DD-Mon-YYYY' in a new column.
